pyddp-0.4.0.dist-info/RECORD
pyddp-0.4.0.dist-info/top_level.txt
pyddp-0.4.0.dist-info/DESCRIPTION.rst
pyddp-0.4.0.dist-info/METADATA
pyddp-0.4.0.dist-info/WHEEL
pyddp-0.4.0.dist-info/metadata.json
ddp/concurrent_ddp_client.py
ddp/utils.py
ddp/__init__.py
ddp/id_generator.py
ddp/ddp_client.py
ddp/pod/__init__.py
ddp/pod/pod_message_parser.py
ddp/pod/pod_message_filter.py
ddp/pod/pod_message_serializer.py
ddp/pubsub/timeout.py
ddp/pubsub/socket_publisher.py
ddp/pubsub/message_serializer.py
ddp/pubsub/__init__.py
ddp/pubsub/socket_reconnector.py
ddp/pubsub/message_parser.py
ddp/pubsub/ddp_connector.py
ddp/pubsub/pod_message_parser.py
ddp/pubsub/subscriber.py
ddp/pubsub/topic.py
ddp/pubsub/socket_publisher_factory.py
ddp/pubsub/outbox.py
ddp/pubsub/topics.py
ddp/pubsub/pod_message_filter.py
ddp/pubsub/socket_connector.py
ddp/pubsub/ponger.py
ddp/pubsub/method_caller.py
ddp/pubsub/logger.py
ddp/pubsub/timeout_error.py
ddp/pubsub/message_board.py
ddp/pubsub/future.py
ddp/pubsub/pod_message_serializer.py
ddp/messages/pong_message_parser.py
ddp/messages/message_serializer.py
ddp/messages/__init__.py
ddp/messages/constants.py
ddp/messages/message.py
ddp/messages/message_parser.py
ddp/messages/ping_message_parser.py
ddp/messages/pong_message.py
ddp/messages/pong_message_serializer.py
ddp/messages/ping_message.py
ddp/messages/ping_message_serializer.py
ddp/messages/client/connect_message_parser.py
ddp/messages/client/sub_message_serializer.py
ddp/messages/client/client_message.py
ddp/messages/client/method_message.py
ddp/messages/client/__init__.py
ddp/messages/client/constants.py
ddp/messages/client/sub_message.py
ddp/messages/client/unsub_message.py
ddp/messages/client/unsub_message_serializer.py
ddp/messages/client/method_message_factory.py
ddp/messages/client/connect_message.py
ddp/messages/client/method_message_parser.py
ddp/messages/client/client_message_serializer.py
ddp/messages/client/connect_message_serializer.py
ddp/messages/client/client_message_parser.py
ddp/messages/client/unsub_message_parser.py
ddp/messages/client/method_message_serializer.py
ddp/messages/client/sub_message_parser.py
