Metadata-Version: 2.0
Name: pyddp
Version: 0.4.0
Summary: Distributed Data Protocol (DDP)
Home-page: https://github.com/foxdog-studios/pyddp
Author: Peter Sutton
Author-email: foxxy@foxdogstudios.com
License: Apache License v2.0
Platform: UNKNOWN
Classifier: Development Status :: 1 - Planning
Classifier: Environment :: Web Environment
Classifier: Intended Audience :: Developers
Classifier: License :: OSI Approved :: Apache Software License
Classifier: Operating System :: OS Independent
Classifier: Programming Language :: Python
Classifier: Topic :: Internet
Classifier: Topic :: Software Development :: Libraries :: Python Modules
Requires-Dist: autobahn[asyncio,accelerate]
Requires-Dist: trollius (==0.3)
